b64_regex/__init__.py
b64_regex/generate_test.py
b64_regex/recoder.py
b64_regex/tests/__init__.py
b64_regex/tests/data/test.csv
b64_regex/tests/data/test.txt
b64_regex/tests/test_compiler.py
b64_regex-0.1.2.dist-info/METADATA
b64_regex-0.1.2.dist-info/WHEEL
b64_regex-0.1.2.dist-info/RECORD
