Metadata-Version: 2.1
Name: b64-regex
Version: 0.1.2
Summary: Build regex patterns for searching through b64 encoded text without decoding.
Home-page: https://github.com/MythicManiac/b64-regex
License: MIT
Author: Mythic
Author-email: mythic@thunderstore.io
Requires-Python: >=3.8,<4.0
Classifier: License :: OSI Approved :: MIT License
Classifier: Programming Language :: Python :: 3
Classifier: Programming Language :: Python :: 3.8
Classifier: Programming Language :: Python :: 3.9
Classifier: Programming Language :: Python :: 3.10
Classifier: Programming Language :: Python :: 3.11
Project-URL: Repository, https://github.com/MythicManiac/b64-regex
